zenith_analyser/__init__.py
zenith_analyser/analysers.py
zenith_analyser/cli.py
zenith_analyser/constants.py
zenith_analyser/exceptions.py
zenith_analyser/lexer.py
zenith_analyser/metrics.py
zenith_analyser/parser.py
zenith_analyser/unparser.py
zenith_analyser/utils.py
zenith_analyser/validator.py
zenith_analyser/visuals.py
zenith_analyser-1.1.0.dist-info/licenses/AUTHORS.md
zenith_analyser-1.1.0.dist-info/licenses/LICENSE
zenith_analyser-1.1.0.dist-info/licenses/NOTICE
zenith_analyser-1.1.0.dist-info/METADATA
zenith_analyser-1.1.0.dist-info/WHEEL
zenith_analyser-1.1.0.dist-info/entry_points.txt
zenith_analyser-1.1.0.dist-info/top_level.txt
zenith_analyser-1.1.0.dist-info/RECORD
