Metadata-Version: 2.4
Name: zenith-analyser
Version: 1.1.0
Summary: A library for analyzing structured temporal laws
Author-email: François TUMUSAVYEYESU <frasasudev@gmail.com>
License:                                   Apache License
Keywords: temporal,chronology,dsl,parser,analysis,simulation,zenith
Classifier: Programming Language :: Python :: 3
Classifier: Programming Language :: Python :: 3.8
Classifier: Programming Language :: Python :: 3.9
Classifier: Programming Language :: Python :: 3.10
Classifier: Programming Language :: Python :: 3.11
Classifier: Programming Language :: Python :: 3.12
Classifier: License :: OSI Approved :: Apache Software License
Classifier: Operating System :: OS Independent
Classifier: Topic :: Software Development :: Libraries :: Python Modules
Classifier: Intended Audience :: Developers
Classifier: Development Status :: 5 - Production/Stable
Requires-Python: >=3.8
License-File: LICENSE
License-File: NOTICE
License-File: AUTHORS.md
Requires-Dist: pandas<3.0,>=2.0
Requires-Dist: matplotlib<4.0,>=3.7
Requires-Dist: numpy>=1.22.0
Provides-Extra: dev
Requires-Dist: black>=23.0.0; extra == "dev"
Requires-Dist: flake8>=6.0.0; extra == "dev"
Requires-Dist: mypy>=1.0.0; extra == "dev"
Requires-Dist: pytest>=7.0.0; extra == "dev"
Requires-Dist: pytest-cov>=4.0.0; extra == "dev"
Dynamic: license-file
